MANIFEST.in
README.rst
pcleanurls
pdetinyfy
plag
pmerge
ptweetlen
puniq
puniqrt
purls
purltitle
setup.py
PipeTK.egg-info/PKG-INFO
PipeTK.egg-info/SOURCES.txt
PipeTK.egg-info/dependency_links.txt
PipeTK.egg-info/requires.txt
PipeTK.egg-info/top_level.txt
bin/pipetk
pipetk/__init__.py
pipetk/pipetk.py