Metadata-Version: 1.1
Name: PipeTK
Version: 0.2.5.1
Summary: Collection of small scripts that modify input received via shell pipe
Home-page: http://worlddomination.be/projects/pipetk.html
Author: Laurent Peuch
Author-email: cortex@worlddomination.be
License: GPLv3+
Keywords: sh bash shell pipe stream cli
Platform: UNKNOWN
Classifier: Development Status :: 4 - Beta
Classifier: Environment :: Console
Classifier: Intended Audience :: End Users/Desktop
Classifier: License :: OSI Approved :: GNU General Public License (GPL)
Classifier: Programming Language :: Python
